{
  "blocks": {
    "languageVersion": 0,
    "blocks": [
      {
        "type": "arduino_setup",
        "id": "b1",
        "x": 20,
        "y": 20,
        "inputs": {
          "BODY": {
            "block": {
              "type": "pin_mode",
              "id": "b2",
              "fields": {
                "PIN": 13,
                "MODE": "OUTPUT"
              }
            }
          }
        }
      },
      {
        "type": "arduino_loop",
        "id": "b3",
        "x": 20,
        "y": 160,
        "inputs": {
          "BODY": {
            "block": {
              "type": "digital_write",
              "id": "b4",
              "fields": {
                "PIN": 13,
                "VALUE": "HIGH"
              },
              "next": {
                "block": {
                  "type": "delay_ms",
                  "id": "b5",
                  "fields": {
                    "MS": 1000
                  },
                  "next": {
                    "block": {
                      "type": "digital_write",
                      "id": "b6",
                      "fields": {
                        "PIN": 13,
                        "VALUE": "LOW"
                      },
                      "next": {
                        "block": {
                          "type": "delay_ms",
                          "id": "b7",
                          "fields": {
                            "MS": 1000
                          }
                        }
                      }
                    }
                  }
                }
              }
            }
          }
        }
      }
    ]
  }
}
